treaz/__init__.py
treaz/main.py
treaz-2.0.0.dist-info/licenses/LICENSE
treaz-2.0.0.dist-info/METADATA
treaz-2.0.0.dist-info/WHEEL
treaz-2.0.0.dist-info/entry_points.txt
treaz-2.0.0.dist-info/top_level.txt
treaz-2.0.0.dist-info/RECORD
