Metadata-Version: 2.4
Name: treaz
Version: 2.0.0
Summary: Mysterious system & network reconnaissance tool
Author: ervuln
License: Apache-2.0
Keywords: system,recon,network,hacker,terminal,monitoring,tool,security,cyber,pentest
Classifier: Development Status :: 4 - Beta
Classifier: Topic :: System :: Monitoring
Classifier: License :: OSI Approved :: Apache Software License
Classifier: Programming Language :: Python :: 3
Classifier: Programming Language :: Python :: 3.9
Requires-Python: >=3.8
License-File: LICENSE
Requires-Dist: psutil
Requires-Dist: requests
Requires-Dist: colorama
Requires-Dist: rich
Requires-Dist: shutilwhich; platform_system != "Windows"
Requires-Dist: wmi; platform_system == "Windows"
Dynamic: license-file
Dynamic: requires-python
